figcan/__init__.py
figcan/figcan.py
figcan/py.typed
figcan-0.0.4.dist-info/LICENSE
figcan-0.0.4.dist-info/METADATA
figcan-0.0.4.dist-info/WHEEL
figcan-0.0.4.dist-info/top_level.txt
figcan-0.0.4.dist-info/RECORD
