Metadata-Version: 2.1
Name: figcan
Version: 0.0.4
Summary: Figcan - minimalistic configuration handling library for Python
Home-page: https://github.com/shoppimon/figcan
Author: Shahar Evron
Author-email: shahar@shoppimon.com
License: Apache 2.0
Keywords: configuration config management yaml json ini arguments simple
Platform: UNKNOWN
Requires-Python: >=2.7.12,!=3.0.*,!=3.1.*,!=3.2.*,!=3.3.*
Requires-Dist: typing; python_version < "3.0"
